pycrashreport/__init__.py
pycrashreport/__main__.py
pycrashreport/_version.py
pycrashreport/crash_report.py
pycrashreport-1.2.5.dist-info/LICENSE
pycrashreport-1.2.5.dist-info/METADATA
pycrashreport-1.2.5.dist-info/WHEEL
pycrashreport-1.2.5.dist-info/entry_points.txt
pycrashreport-1.2.5.dist-info/top_level.txt
pycrashreport-1.2.5.dist-info/RECORD
