Metadata-Version: 2.1
Name: pycrashreport
Version: 1.2.5
Summary: Pure python3 for parsing Apple's crash reports
Author-email: doronz88 <doron88@gmail.com>
Maintainer-email: doronz88 <doron88@gmail.com>
License:                     GNU GENERAL PUBLIC LICENSE
Project-URL: Homepage, https://github.com/doronz88/pycrashreport
Project-URL: Bug Reports, https://github.com/doronz88/pycrashreport/issues
Keywords: ios,cli,macos,parser,crash
Classifier: Development Status :: 5 - Production/Stable
Classifier: License :: OSI Approved :: GNU General Public License v3 or later (GPLv3+)
Classifier: Programming Language :: Python :: 3
Classifier: Programming Language :: Python :: 3.8
Classifier: Programming Language :: Python :: 3.9
Classifier: Programming Language :: Python :: 3.10
Classifier: Programming Language :: Python :: 3.11
Classifier: Programming Language :: Python :: 3.12
Classifier: Programming Language :: Python :: 3 :: Only
Requires-Python: >=3.8
License-File: LICENSE
Requires-Dist: click
Requires-Dist: cached_property
Requires-Dist: la_panic==0.5.0
Provides-Extra: test
Requires-Dist: pytest; extra == "test"
